ER_1OCTET/er_1octet.vhd
library IEEE;
use IEEE.STD_LOGIC_1164.ALL;

entity er_1octet is
  port ( rst : in std_logic ;				--signal du reset 
         clk : in std_logic ;				--clock du circuit
         en : in std_logic ;				--signal du enable, pour activer l'envoi/reception
         din : in std_logic_vector (7 downto 0) ;	--octet recu
         miso : in std_logic ;				--signal envoi du bit du slave vers le master 
         sclk : out std_logic ;				--clock interne du composant actif lors de l'envoi/reception
         mosi : out std_logic ;				--signal envoi du bit du master vers le slave 
         dout : out std_logic_vector (7 downto 0) ;	--octet a envoyer
         busy : out std_logic);				--signal d'activite
end er_1octet;	

architecture behavioral_3 of er_1octet is

type t_etat is (idle, envoi_data, reception_data);	--les etats de l'automate 
signal etat : t_etat;					--etat en cours

begin
 

  process(clk, rst)
  
  variable cpt_bit : natural;				--compteur d'envoi/reception pour l'emplacement du bit dans le registre
  variable registre : std_logic_vector(7 downto 0);	--registre qui permet de stocker l'octet a envoyer et celui recu 
 
   
  begin

	

    if(rst = '0') then 					--en faisant un reset, le registre est nettoye et le circuit passe en attente 

      cpt_bit := 7;			

      registre := (others => 'U');
		
		dout <= (others => '0');
		
		mosi <= '0';
		
		sclk <= '1';
		
		busy <= '0';
		
      etat <= idle;					
		
     elsif(rising_edge(clk)) then

      case etat is

        when idle =>					--si le composant est actif, on passe aux etats envoi/reception
        
          if(en = '1') then			 	
          
            busy <= '1';
				
				sclk <= '0';		
				
				cpt_bit := 7;
				
            registre := din;

            mosi <= registre(cpt_bit);			--le circuit envoi le premir bit lors de la transition d'etats pour augmenter l'efficacite
			
            etat <= reception_data;			

          else
           
				null;
				
          end if;
          
        when envoi_data =>
      
				mosi <= registre(cpt_bit);	
				
				sclk <= '0';			
	     
				etat <= reception_data;
	    		
        when reception_data =>
           
			  if (cpt_bit > 0) then 				--a la fin de l'envoi/reception, le circuit passe en attente
				
				 registre(cpt_bit) := miso;
					
				 cpt_bit := cpt_bit - 1;
				
				 sclk <= '1';				--le circuit envoi un bit du registre et le remplace par le bit recu pour l'efficacite de la memoire
						
				 --busy <= '1';
					
				 etat <= envoi_data;
							
				else 
					
					registre(cpt_bit) := miso;
				
					dout <= registre;
					
					sclk <= '1';
					
					busy <= '0';
					
				   etat <= idle;
				
				end if;	
      
		end case;
    
	 end if;
  
  end process;

end behavioral_3;

ER_1OCTET/test_er_1octet_simple.vhd
library IEEE;
use IEEE.STD_LOGIC_1164.ALL;

entity test_er_1octet is
  end test_er_1octet;

architecture behavior of test_er_1octet is

  component er_1octet
    port ( rst : in std_logic;
           clk : in std_logic;
           en : in std_logic;
           din : in std_logic_vector (7 downto 0);
           miso : in std_logic;
           sclk : out std_logic;
           mosi : out std_logic;
           dout : out std_logic_vector (7 downto 0);
           busy : out std_logic);
  end component;

  --Inputs
  signal clk : std_logic := '0';
  signal reset : std_logic := '0';
  signal en : std_logic := '0';
  signal din : std_logic_vector(7 downto 0) := (others => '0');
  signal miso : std_logic := '0';

  --Outputs
  signal busy : std_logic;
  signal dout : std_logic_vector(7 downto 0);
  signal sclk : std_logic;
  signal mosi : std_logic;

  --References
  signal busy_ref : std_logic;
  signal dout_ref : std_logic_vector(7 downto 0);
  signal sclk_ref : std_logic;
  signal mosi_ref : std_logic;

  -- Clock period definitions
  constant clk_period : time := 10 ns;

begin

  m : er_1octet
  port map ( clk => clk,
             rst => reset,
             en => en,
             busy => busy,
             din => din,
             dout => dout,
             sclk => sclk,
             miso => miso,
             mosi => mosi
           );

  clk_process : process
  begin
    clk <= '0';
    wait for clk_period/2;
    clk <= '1';
    wait for clk_period/2;
  end process;


  -- Stimulus process
  stim_proc: process
  begin                
    -- hold reset state for 100 ns.
    wait for 100 ns;  
    reset <= '1';

    wait for clk_period*10;

    -- insert stimulus here

    din <= "10110101";

    en <= '1';

    wait for clk_period;

    en <= '0';
    din <= (others => 'U');

    wait for 21*clk_period;

    din <= "00110100";

    en <= '1';

    wait for clk_period;

    en <= '0';
    din <= (others => 'U');

    wait;
  end process;

  genere_miso : process(clk, reset)

    variable cpt : natural;

  begin

    if(reset = '0') then
      miso <= '0';
      cpt := 0;
    elsif(falling_edge(clk)) then
      cpt := (cpt + 1) mod 7;
      if(cpt < 3) then
        miso <= '0';
      else
        miso <= '1';
      end if;                  
    end if;

  end process genere_miso;

  --
  -- pour vérifier si mosi, sclk et busy et dout sont corrects

  busy_ref <= '0' after 0 ps,
              '1' after 205000 ps,
              '0' after 355000 ps,
              '1' after 425000 ps,
              '0' after 575000 ps;

  dout_ref <= "00000000" after 0 ps,
              "10011011" after 355000 ps,
              "10110011" after 575000 ps;

  mosi_ref <= '0' after 0 ps,
              '1' after 205000 ps,
              '0' after 225000 ps,
              '1' after 245000 ps,
              '0' after 285000 ps,
              '1' after 305000 ps,
              '0' after 325000 ps,
              '1' after 345000 ps,
              '0' after 425000 ps,
              '1' after 465000 ps,
              '0' after 505000 ps,
              '1' after 525000 ps,
              '0' after 545000 ps;

  sclk_ref <= '1' after 0 ps,
              '0' after 205000 ps,
              '1' after 215000 ps,
              '0' after 225000 ps,
              '1' after 235000 ps,
              '0' after 245000 ps,
              '1' after 255000 ps,
              '0' after 265000 ps,
              '1' after 275000 ps,
              '0' after 285000 ps,
              '1' after 295000 ps,
              '0' after 305000 ps,
              '1' after 315000 ps,
              '0' after 325000 ps,
              '1' after 335000 ps,
              '0' after 345000 ps,
              '1' after 355000 ps,
              '0' after 425000 ps,
              '1' after 435000 ps,
              '0' after 445000 ps,
              '1' after 455000 ps,
              '0' after 465000 ps,
              '1' after 475000 ps,
              '0' after 485000 ps,
              '1' after 495000 ps,
              '0' after 505000 ps,
              '1' after 515000 ps,
              '0' after 525000 ps,
              '1' after 535000 ps,
              '0' after 545000 ps,
              '1' after 555000 ps,
              '0' after 565000 ps,
              '1' after 575000 ps;

  process(clk)
  begin
    if(falling_edge(clk)) then
      assert(mosi = mosi_ref) report "mosi faux"
      severity error;
      assert(sclk = sclk_ref) report "sclk faux"
      severity error;
      assert(busy = busy_ref) report "busy faux"
      severity error;
      assert(dout = dout_ref) report "dout faux"
      severity error;
    end if;
  end process;

end behavior;

ER_1OCTET/output.vcd
$date
   Tue Nov 23 15:04:10 2021
$end
$version
  P.20131013
$end
$timescale
  1ps
$end
$scope module test_er_1octet $end
$var wire 1 D clk $end
$var wire 1 C reset $end
$var wire 1 E en $end
$var wire 1 M din [7] $end
$var wire 1 L din [6] $end
$var wire 1 K din [5] $end
$var wire 1 J din [4] $end
$var wire 1 I din [3] $end
$var wire 1 H din [2] $end
$var wire 1 G din [1] $end
$var wire 1 F din [0] $end
$var wire 1 N miso $end
$var wire 1 Y busy $end
$var wire 1 X dout [7] $end
$var wire 1 W dout [6] $end
$var wire 1 V dout [5] $end
$var wire 1 U dout [4] $end
$var wire 1 T dout [3] $end
$var wire 1 S dout [2] $end
$var wire 1 R dout [1] $end
$var wire 1 Q dout [0] $end
$var wire 1 O sclk $end
$var wire 1 P mosi $end
$var wire 1 8 busy_ref $end
$var wire 1 @ dout_ref [7] $end
$var wire 1 ? dout_ref [6] $end
$var wire 1 > dout_ref [5] $end
$var wire 1 = dout_ref [4] $end
$var wire 1 < dout_ref [3] $end
$var wire 1 ; dout_ref [2] $end
$var wire 1 : dout_ref [1] $end
$var wire 1 9 dout_ref [0] $end
$var wire 1 A sclk_ref $end
$var wire 1 B mosi_ref $end
$scope module m $end
$var wire 1 C rst $end
$var wire 1 D clk $end
$var wire 1 E en $end
$var wire 1 M din [7] $end
$var wire 1 L din [6] $end
$var wire 1 K din [5] $end
$var wire 1 J din [4] $end
$var wire 1 I din [3] $end
$var wire 1 H din [2] $end
$var wire 1 G din [1] $end
$var wire 1 F din [0] $end
$var wire 1 N miso $end
$var wire 1 O sclk $end
$var wire 1 P mosi $end
$var wire 1 X dout [7] $end
$var wire 1 W dout [6] $end
$var wire 1 V dout [5] $end
$var wire 1 U dout [4] $end
$var wire 1 T dout [3] $end
$var wire 1 S dout [2] $end
$var wire 1 R dout [1] $end
$var wire 1 Q dout [0] $end
$var wire 1 Y busy $end
$upscope $end
$upscope $end
$enddefinitions $end
#0
$dumpvars
0C
0D
0M
0L
0K
0J
0I
0H
0G
0F
0N
0Y
0X
0W
0V
0U
0T
0S
0R
0Q
1O
0P
08
0@
0?
0>
0=
0<
0;
0:
09
1A
0B
0E
$end
#5000
1D
#10000
0D
#15000
1D
#20000
0D
#25000
1D
#30000
0D
#35000
1D
#40000
0D
#45000
1D
#50000
0D
#55000
1D
#60000
0D
#65000
1D
#70000
0D
#75000
1D
#80000
0D
#85000
1D
#90000
0D
#95000
1D
#100000
1C
0D
#105000
1D
#110000
0D
#115000
1D
#120000
0D
1N
#125000
1D
#130000
0D
#135000
1D
#140000
0D
#145000
1D
#150000
0D
#155000
1D
#160000
0D
0N
#165000
1D
#170000
0D
#175000
1D
#180000
0D
#185000
1D
#190000
0D
1N
#195000
1D
#200000
0D
1M
1K
1J
1H
1F
1E
#205000
1D
1Y
0O
1P
18
0A
1B
#210000
0D
xM
xL
xK
xJ
xI
xH
xG
xF
0E
#215000
1D
1O
1A
#220000
0D
#225000
1D
0O
0P
0A
0B
#230000
0D
0N
#235000
1D
1O
1A
#240000
0D
#245000
1D
0O
1P
0A
1B
#250000
0D
#255000
1D
1O
1A
#260000
0D
1N
#265000
1D
0O
0A
#270000
0D
#275000
1D
1O
1A
#280000
0D
#285000
1D
0O
0P
0A
0B
#290000
0D
#295000
1D
1O
1A
#300000
0D
0N
#305000
1D
0O
1P
0A
1B
#310000
0D
#315000
1D
1O
1A
#320000
0D
#325000
1D
0O
0P
0A
0B
#330000
0D
1N
#335000
1D
1O
1A
#340000
0D
#345000
1D
0O
1P
0A
1B
#350000
0D
#355000
1D
0Y
1X
1U
1T
1R
1Q
1O
08
1@
1=
1<
1:
19
1A
#360000
0D
#365000
1D
#370000
0D
0N
#375000
1D
#380000
0D
#385000
1D
#390000
0D
#395000
1D
#400000
0D
1N
#405000
1D
#410000
0D
#415000
1D
#420000
0D
0M
0L
1K
1J
0I
1H
0G
0F
1E
#425000
1D
1Y
0O
0P
18
0A
0B
#430000
0D
xM
xL
xK
xJ
xI
xH
xG
xF
0E
#435000
1D
1O
1A
#440000
0D
0N
#445000
1D
0O
0A
#450000
0D
#455000
1D
1O
1A
#460000
0D
#465000
1D
0O
1P
0A
1B
#470000
0D
1N
#475000
1D
1O
1A
#480000
0D
#485000
1D
0O
0A
#490000
0D
#495000
1D
1O
1A
#500000
0D
#505000
1D
0O
0P
0A
0B
#510000
0D
0N
#515000
1D
1O
1A
#520000
0D
#525000
1D
0O
1P
0A
1B
#530000
0D
#535000
1D
1O
1A
#540000
0D
1N
#545000
1D
0O
0P
0A
0B
#550000
0D
#555000
1D
1O
1A
#560000
0D
#565000
1D
0O
0A
#570000
0D
#575000
1D
0Y
1V
0T
1O
08
1>
0<
1A
#580000
0D
0N
#585000
1D
#590000
0D
#595000
1D
#600000
0D
#605000
1D
#610000
0D
1N
#615000
1D
#620000
0D
#625000
1D
#630000
0D
#635000
1D
#640000
0D
#645000
1D
#650000
0D
0N
#655000
1D
#660000
0D
#665000
1D
#670000
0D
#675000
1D
#680000
0D
1N
